davidoc/__init__.py
davidoc/__main__.py
davidoc/app.py
davidoc/apps/__init__.py
davidoc/apps/services/__init__.py
davidoc/apps/services/main.py
davidoc/apps/services/prescriptions.py
davidoc/apps/services/visits.py
davidoc/apps/users/__init__.py
davidoc/apps/users/doctors.py
davidoc/apps/users/main.py
davidoc/apps/users/patients.py
davidoc/apps/utils/__init__.py
davidoc/apps/utils/main.py
davidoc/core/__init__.py
davidoc/core/db.py
davidoc/core/orm.py
davidoc/core/settings.py
davidoc/dataparsin/__init__.py
davidoc/dataparsin/base.py
davidoc/dataparsin/doctors.py
davidoc/dataparsin/patients.py
davidoc/dataparsin/users.py
davidoc/dataparsin/visits.py
davidoc-0.1.0.dist-info/entry_points.txt
davidoc-0.1.0.dist-info/WHEEL
davidoc-0.1.0.dist-info/METADATA
davidoc-0.1.0.dist-info/RECORD
